odoo/addons/fieldservice_stock_account/README.rst
odoo/addons/fieldservice_stock_account/__init__.py
odoo/addons/fieldservice_stock_account/__manifest__.py
odoo/addons/fieldservice_stock_account/i18n/de.po
odoo/addons/fieldservice_stock_account/i18n/es.po
odoo/addons/fieldservice_stock_account/i18n/es_CL.po
odoo/addons/fieldservice_stock_account/i18n/fieldservice_stock_account.pot
odoo/addons/fieldservice_stock_account/i18n/pt_BR.po
odoo/addons/fieldservice_stock_account/models/__init__.py
odoo/addons/fieldservice_stock_account/models/fsm_order.py
odoo/addons/fieldservice_stock_account/readme/CONTRIBUTORS.rst
odoo/addons/fieldservice_stock_account/readme/CREDITS.rst
odoo/addons/fieldservice_stock_account/readme/DESCRIPTION.rst
odoo/addons/fieldservice_stock_account/readme/USAGE.rst
odoo/addons/fieldservice_stock_account/static/description/icon.png
odoo/addons/fieldservice_stock_account/static/description/index.html
odoo12_addon_fieldservice_stock_account-12.0.2.0.0.dist-info/METADATA
odoo12_addon_fieldservice_stock_account-12.0.2.0.0.dist-info/WHEEL
odoo12_addon_fieldservice_stock_account-12.0.2.0.0.dist-info/top_level.txt
odoo12_addon_fieldservice_stock_account-12.0.2.0.0.dist-info/RECORD
