Metadata-Version: 2.1
Name: odoo12-addon-fieldservice-stock-account
Version: 12.0.2.0.0
Summary: Invoice inventory items delivered with Field Service orders
Home-page: https://github.com/OCA/field-service
Author: Open Source Integrators, Odoo Community Association (OCA)
Author-email: support@odoo-community.org
License: AGPL-3
Platform: UNKNOWN
Classifier: Programming Language :: Python
Classifier: Framework :: Odoo
Classifier: License :: OSI Approved :: GNU Affero General Public License v3
Classifier: Development Status :: 4 - Beta
Requires-Python: >=3.5
Requires-Dist: odoo12-addon-account-invoice-report-hide-line
Requires-Dist: odoo12-addon-fieldservice-account
Requires-Dist: odoo12-addon-fieldservice-stock-request
Requires-Dist: odoo (<12.1dev,>=12.0a)
